fastod/__init__.py
fastod/push_project.py
fastod/tools.py
fastod/_test/1 connect_mysql.py
fastod/_test/2 query.py
fastod/_test/3 gen.py
fastod/core/__init__.py
fastod/core/db.py
fastod/core/table.py
fastod-0.2.6.dist-info/METADATA
fastod-0.2.6.dist-info/WHEEL
fastod-0.2.6.dist-info/top_level.txt
fastod-0.2.6.dist-info/RECORD
