Metadata-Version: 2.4
Name: fastod
Version: 0.2.6
Summary: Fast Operation Database
Author-email: WangTuo <markadc@126.com>
License-Expression: MIT
Project-URL: Homepage, https://github.com/markadc/fastod
Requires-Python: >=3.10
Requires-Dist: DBUtils
Requires-Dist: PyMySQL
Requires-Dist: Faker
Requires-Dist: loguru
